MANIFEST.in
README.rst
TITLE.txt
lh-agpl3-LICENSE.txt
setup.py
./bin/fileParamManage.py
./bin/fileTreeManage.py
unisos2/__init__.py
unisos2.common.egg-info/PKG-INFO
unisos2.common.egg-info/SOURCES.txt
unisos2.common.egg-info/dependency_links.txt
unisos2.common.egg-info/namespace_packages.txt
unisos2.common.egg-info/not-zip-safe
unisos2.common.egg-info/requires.txt
unisos2.common.egg-info/top_level.txt
unisos2/common/__init__.py
unisos2/common/icmCmndsRun.py
unisos2/common/icmsPkgLib.py
unisos2/common/new-icmCmndsRun.py